vdbmanager/ThothHaystackVectorStore.py
vdbmanager/ThothVectorStore.py
vdbmanager/__init__.py
vdbmanager/impl/QdrantHaystackStore.py
vdbmanager/impl/__init__.py
thoth_vdb-0.1.8.dist-info/METADATA
thoth_vdb-0.1.8.dist-info/WHEEL
thoth_vdb-0.1.8.dist-info/top_level.txt
thoth_vdb-0.1.8.dist-info/RECORD
