Metadata-Version: 2.4
Name: thoth-vdb
Version: 0.1.8
Summary: A vector database management module for Thoth Project
Author-email: Marco Pancotti <mp@tylconsulting.it>
Project-URL: Homepage, https://github.com/yourusername/thoth_vdb
Project-URL: Bug Tracker, https://github.com/yourusername/thoth_vdb/issues
Classifier: Programming Language :: Python :: 3
Classifier: License :: OSI Approved :: MIT License
Classifier: Operating System :: OS Independent
Requires-Python: >=3.8
Requires-Dist: annotated-types==0.7.0
Requires-Dist: anyio==4.9.0
Requires-Dist: attrs==25.3.0
Requires-Dist: backoff==2.2.1
Requires-Dist: certifi==2025.1.31
Requires-Dist: charset-normalizer==3.4.1
Requires-Dist: construct==2.5.3
Requires-Dist: distro==1.9.0
Requires-Dist: grpcio==1.71.0
Requires-Dist: grpcio-tools==1.71.0
Requires-Dist: h11==0.14.0
Requires-Dist: h2==4.2.0
Requires-Dist: haystack==0.42
Requires-Dist: haystack-ai==2.12.2
Requires-Dist: haystack-experimental==0.9.0
Requires-Dist: sentence-transformers
Requires-Dist: hpack==4.1.0
Requires-Dist: httpcore==1.0.8
Requires-Dist: httpx==0.28.1
Requires-Dist: hyperframe==6.1.0
Requires-Dist: idna==3.10
Requires-Dist: Jinja2==3.1.6
Requires-Dist: jiter==0.9.0
Requires-Dist: jsonschema==4.23.0
Requires-Dist: jsonschema-specifications==2024.10.1
Requires-Dist: lazy_imports==0.4.0
Requires-Dist: MarkupSafe==3.0.2
Requires-Dist: monotonic==1.6
Requires-Dist: more-itertools==10.6.0
Requires-Dist: networkx==3.4.2
Requires-Dist: numpy==2.2.4
Requires-Dist: openai==1.75.0
Requires-Dist: pefile==2024.8.26
Requires-Dist: portalocker==2.10.1
Requires-Dist: posthog==3.25.0
Requires-Dist: protobuf==5.29.4
Requires-Dist: pydantic==2.11.3
Requires-Dist: pydantic_core==2.33.1
Requires-Dist: python-dateutil==2.9.0.post0
Requires-Dist: python-ptrace==0.9.9
Requires-Dist: PyYAML==6.0.2
Requires-Dist: qdrant-client==1.13.3
Requires-Dist: qdrant-haystack==9.1.1
Requires-Dist: referencing==0.36.2
Requires-Dist: requests==2.32.3
Requires-Dist: rpds-py==0.24.0
Requires-Dist: six==1.17.0
Requires-Dist: sniffio==1.3.1
Requires-Dist: tenacity==9.1.2
Requires-Dist: tqdm==4.67.1
Requires-Dist: typing-inspection==0.4.0
Requires-Dist: typing_extensions==4.13.2
Requires-Dist: urllib3==2.4.0
Provides-Extra: test
Requires-Dist: pytest; extra == "test"
